README.md
files.py
setup.py
procfiles.egg-info/PKG-INFO
procfiles.egg-info/SOURCES.txt
procfiles.egg-info/dependency_links.txt
procfiles.egg-info/top_level.txt