Metadata-Version: 2.1
Name: procfiles
Version: 0.1
Summary: Pacote para manipulação de arquivos e pastas
Home-page: https://github.com/marciofreitas71/procfiles
Author: Marcio Freitas
Author-email: marciofreitas71@yahoo.com.br
